interchange/__init__.py
interchange/collections.py
interchange/geo.py
interchange/math.py
interchange/packstream.py
interchange/text.py
interchange/time.py
interchange-2021.0.4.dist-info/LICENSE
interchange-2021.0.4.dist-info/METADATA
interchange-2021.0.4.dist-info/WHEEL
interchange-2021.0.4.dist-info/top_level.txt
interchange-2021.0.4.dist-info/RECORD
